gami/__init__.py
gami/_version.py
gami/conftest.py
gami/model.py
gami-0.0.16.dist-info/LICENSE
gami-0.0.16.dist-info/METADATA
gami-0.0.16.dist-info/WHEEL
gami-0.0.16.dist-info/top_level.txt
gami-0.0.16.dist-info/RECORD
